{
    "initialization": {
        "initializing": "[prefix] Initializing!",
        "language": "The system is using the [language] language and the default language for the functions is [default].",
        "version": "You're Using the Version [version] Based on ArunaBot",
        "complete": "Initialization Complete!",
        "fail": "Failed to initialize:"
    },
    "main": {
        "error": "ERROR",
        "event": "EVENT",
        "events": "EVENTS",
        "command": "COMMAND",
        "commands": "COMMANDS",
        "cluster": "CLUSTER",
        "registered": "[COMMAND] registered in the database as configurable."
    },
    "shard": {
        "master": "SHARD MASTER",
        "launch": "[shard] Were initialized",
        "exit": "A process was forced to be closed.",
        "exitCode": "Exit Code:",
        "startGeneration": "[logPrefix] Starting Shards generation...",
        "finishGeneration": "Finishing Shards generation..."
    },
    "generic": {
        "base": "Base",
        "connected": "=> Connected!",
        "core": "Core",
        "languageName": "English",
        "notFound": "Not Found!",
        "shard": "Shard"
    }
}